<?xml version = '1.0' encoding = 'UTF-8'?>
<Relation class="oracle.dbtools.crest.model.design.logical.Relation" name="rbc_obu" directorySegmentName="seg_0" id="D934EB20-7373-ABE9-70B3-6F8C04519A75">
<createdBy>Pecen</createdBy>
<createdTime>2023-07-31 13:32:53 UTC</createdTime>
<commentInRDBMS><![CDATA[assigned cryptographic keys]]></commentInRDBMS>
<ownerDesignName>tickets</ownerDesignName>
<shouldEngineer>false</shouldEngineer>
<engineerTo>
<item key="54351667-7A39-92CB-4D51-D131F2FAE06D" value="false"/>
</engineerTo>
<sourcePk>EAD94329-BAD4-AE9D-6EDD-EB78E87FD96F</sourcePk>
<identifying>false</identifying>
<optionalSource>true</optionalSource>
<optionalTarget>true</optionalTarget>
<sourceCardinality>*</sourceCardinality>
<sourceEntity>5EADCBE0-4BAA-EAD7-A9A4-ECBC8F32136E</sourceEntity>
<targetCardinalityString>*</targetCardinalityString>
<targetEntity>F5009D01-7E4C-86DA-3087-C6DEF7C78E2B</targetEntity>
<transferable>true</transferable>
<deleteRule>CASCADE</deleteRule>
</Relation>
